FiberPhotometryDataAnalysis/FiberPhotometryDataAnalysis.py
FiberPhotometryDataAnalysis/__init__.py
FiberPhotometryDataAnalysis/__main__.py
FiberPhotometryDataAnalysis/cli.py
FiberPhotometryDataAnalysis/other_tools.py
FiberPhotometryDataAnalysis/plot_tools.py
FiberPhotometryDataAnalysis/processing_tools.py
FiberPhotometryDataAnalysis/recording.py
FiberPhotometryDataAnalysis/recording_class.py
FiberPhotometryDataAnalysis/recording_module.py
FiberPhotometryDataAnalysis/time_tools.py
FiberPhotometryDataAnalysis-0.0.9.dist-info/AUTHORS.rst
FiberPhotometryDataAnalysis-0.0.9.dist-info/LICENSE
FiberPhotometryDataAnalysis-0.0.9.dist-info/METADATA
FiberPhotometryDataAnalysis-0.0.9.dist-info/WHEEL
FiberPhotometryDataAnalysis-0.0.9.dist-info/entry_points.txt
FiberPhotometryDataAnalysis-0.0.9.dist-info/top_level.txt
FiberPhotometryDataAnalysis-0.0.9.dist-info/RECORD
