Metadata-Version: 2.1
Name: FiberPhotometryDataAnalysis
Version: 0.0.9
Summary: A package for analysis of multi-fiber photmetry data and behaviour.
Home-page: https://https://github.com/katemartian/FiberPhotometryDataAnalysis
Author: Kate Martian
Author-email: ekaterina.martian@gmail.com
License: MIT
Project-URL: Documentation, https://FiberPhotometryDataAnalysis.readthedocs.io/
Project-URL: Changelog, https://FiberPhotometryDataAnalysis.readthedocs.io/en/latest/changelog.html
Project-URL: Issue Tracker, https://https://github.com/katemartian/FiberPhotometryDataAnalysis/issues
Platform: UNKNOWN
Classifier: Development Status :: 5 - Production/Stable
Classifier: Intended Audience :: Developers
Classifier: License :: OSI Approved :: MIT License
Classifier: Operating System :: Unix
Classifier: Operating System :: POSIX
Classifier: Operating System :: Microsoft :: Windows
Classifier: Programming Language :: Python
Classifier: Programming Language :: Python :: 2.7
Classifier: Programming Language :: Python :: 3
Classifier: Programming Language :: Python :: 3.6
Classifier: Programming Language :: Python :: 3.7
Classifier: Programming Language :: Python :: 3.8
Classifier: Programming Language :: Python :: 3.9
Classifier: Programming Language :: Python :: Implementation :: CPython
Classifier: Programming Language :: Python :: Implementation :: PyPy
Classifier: Topic :: Utilities
Requires-Python: >=2.7, !=3.0.*, !=3.1.*, !=3.2.*, !=3.3.*, !=3.4.*, !=3.5.*
License-File: LICENSE
License-File: AUTHORS.rst
